superadmin/__init__.py
superadmin/admin.py
superadmin/apps.py
superadmin/context_processors.py
superadmin/decorators.py
superadmin/forms.py
superadmin/models.py
superadmin/options.py
superadmin/services.py
superadmin/settings.py
superadmin/shortcuts.py
superadmin/signals.py
superadmin/sites.py
superadmin/tests.py
superadmin/utils.py
superadmin/management/__init__.py
superadmin/management/commands/__init__.py
superadmin/management/commands/base.py
superadmin/management/commands/createactions.py
superadmin/management/commands/createbasemenu.py
superadmin/management/commands/createpermission.py
superadmin/management/commands/menu.py
superadmin/migrations/0001_action_menu.py
superadmin/migrations/__init__.py
superadmin/migrations/unaccent_extension.py
superadmin/mixins/__init__.py
superadmin/mixins/breadcrumbs.py
superadmin/mixins/filters.py
superadmin/mixins/inlines.py
superadmin/mixins/permissions.py
superadmin/mixins/templates.py
superadmin/mixins/urls.py
superadmin/mixins/utils.py
superadmin/templatetags/__init__.py
superadmin/templatetags/superadmin_forms.py
superadmin/templatetags/superadmin_utils.py
superadmin/views/__init__.py
superadmin/views/base.py
superadmin/views/create.py
superadmin/views/delete.py
superadmin/views/detail.py
superadmin/views/duplicate.py
superadmin/views/filter.py
superadmin/views/list.py
superadmin/views/update.py
django_superadmin-1.2.6.dist-info/LICENCE
django_superadmin-1.2.6.dist-info/METADATA
django_superadmin-1.2.6.dist-info/WHEEL
django_superadmin-1.2.6.dist-info/top_level.txt
django_superadmin-1.2.6.dist-info/RECORD
