Metadata-Version: 2.1
Name: django-superadmin
Version: 1.2.6
Summary: A Django app for build admin sites like django admin.
Home-page: https://github.com/dbsiavichay/django-superadmin
Author: Denis Siavichay
Author-email: dbsiavichay@gmail.com
License: MIT  # Example license
Platform: UNKNOWN
Classifier: License :: OSI Approved :: MIT License
Classifier: Operating System :: OS Independent
Classifier: Environment :: Web Environment
Classifier: Framework :: Django
Classifier: Framework :: Django :: 2.0
Classifier: Framework :: Django :: 2.1
Classifier: Framework :: Django :: 2.2
Classifier: Framework :: Django :: 3.0
Classifier: Framework :: Django :: 3.1
Classifier: Intended Audience :: Developers
Classifier: Programming Language :: Python
Classifier: Programming Language :: Python :: 3
Classifier: Programming Language :: Python :: 3 :: Only
Classifier: Programming Language :: Python :: 3.5
Classifier: Programming Language :: Python :: 3.6
Classifier: Programming Language :: Python :: 3.7
Classifier: Programming Language :: Python :: 3.8
Classifier: Topic :: Internet :: WWW/HTTP
Classifier: Topic :: Internet :: WWW/HTTP :: Dynamic Content
License-File: LICENCE
Requires-Dist: pyyaml
